perock/__init__.py
perock/_checker.py
perock/_connector.py
perock/_controller.py
perock/_util.py
perock/attack.py
perock/attacks.py
perock/attempt.py
perock/bforce.py
perock/bruteforce.py
perock/check.py
perock/consumer.py
perock/exceptions.py
perock/forcetable.py
perock/handle_data.py
perock/perock.py
perock/producer.py
perock/product.py
perock/responce.py
perock/runner.py
perock/session.py
perock/target.py
perock/util.py
perock-0.2.2.dist-info/LICENSE
perock-0.2.2.dist-info/METADATA
perock-0.2.2.dist-info/WHEEL
perock-0.2.2.dist-info/top_level.txt
perock-0.2.2.dist-info/RECORD
