Metadata-Version: 2.1
Name: perock
Version: 0.2.2
Summary: Simple general purpose python bruteforce library
Home-page: https://github.com/sekgobela-kevin/perock
Author: Sekgobela Kevin
Author-email: kevinnoko23@gmail.com
Project-URL: Bug Tracker, https://github.com/sekgobela-kevin/perock/issues
Keywords: attack,bruteforce,security,testing,hacking,multithreading,asyncio
Classifier: Intended Audience :: Developers
Classifier: Programming Language :: Python :: 3
Classifier: License :: OSI Approved :: GNU General Public License v3 (GPLv3)
Classifier: Operating System :: OS Independent
Classifier: Programming Language :: Python
Classifier: Programming Language :: Python :: 3
Classifier: Topic :: Security
Classifier: Topic :: Software Development
Classifier: Topic :: Software Development :: Libraries
Classifier: Topic :: Software Development :: Libraries :: Python Modules
Requires-Python: >=3.6
License-File: LICENSE
Requires-Dist: prodius (<0.1.0)
Requires-Dist: forcetable (<0.1.0,>=0.0.4)
